README.txt
setup.cfg
setup.py
simplegeo/__init__.py
simplegeo/shared/__init__.py
simplegeo/shared/_version.py
simplegeo/shared/test/__init__.py
simplegeo/shared/test/test_client.py
simplegeo/shared/test/test_record.py
simplegeo_shared.egg-info/PKG-INFO
simplegeo_shared.egg-info/SOURCES.txt
simplegeo_shared.egg-info/dependency_links.txt
simplegeo_shared.egg-info/namespace_packages.txt
simplegeo_shared.egg-info/not-zip-safe
simplegeo_shared.egg-info/requires.txt
simplegeo_shared.egg-info/top_level.txt