Metadata-Version: 1.0
Name: simplegeo-shared
Version: 2.5.127
Summary: Library for interfacing with SimpleGeo's API
Home-page: http://github.com/simplegeo/python-simplegeo-shared
Author: Zooko Wilcox-O'Hearn
Author-email: zooko@simplegeo.com
License: MIT License
Keywords: simplegeo
Platform: UNKNOWN
